moscow_routes_parser/__init__.py
moscow_routes_parser/model.py
moscow_routes_parser/model_impl.py
moscow_routes_parser/t_mos_ru.py
moscow_routes_parser/test_model.py
moscow_routes_parser/test_model_impl.py
moscow_routes_parser/test_t_mos_ru.py
moscow_routes_parser-0.0.16.dist-info/LICENSE.txt
moscow_routes_parser-0.0.16.dist-info/METADATA
moscow_routes_parser-0.0.16.dist-info/WHEEL
moscow_routes_parser-0.0.16.dist-info/top_level.txt
moscow_routes_parser-0.0.16.dist-info/RECORD
